url_for_int/__init__.py
url_for_int/int_gui.py
url_for_int/interpreter.py
url_for_int-2.3.0.dist-info/LICENSE
url_for_int-2.3.0.dist-info/METADATA
url_for_int-2.3.0.dist-info/WHEEL
url_for_int-2.3.0.dist-info/top_level.txt
url_for_int-2.3.0.dist-info/RECORD
