Metadata-Version: 2.1
Name: url-for-int
Version: 2.3.0
Summary: 帮助flask框架中将普通HTML文档转义为url-for的文档
Home-page: https://github.com/Hifive55555/url_for_Int
Author: Hifive
Author-email: 2019912635@qq.com
Classifier: Programming Language :: Python :: 3
Classifier: License :: OSI Approved :: MIT License
Classifier: Operating System :: OS Independent
License-File: LICENSE
